<annotation>
	<folder>images</folder>
	<filename>fire_167.jpg</filename>
	<path>C:\Users\dadan\Documents\Hackathon_Codegreen\Dataset\fire\images\fire_167.jpg</path>
	<source>
		<database>Unknown</database>
	</source>
	<size>
		<width>224</width>
		<height>224</height>
		<depth>3</depth>
	</size>
	<segmented>0</segmented>
	<object>
		<name>smoke</name>
		<pose>Unspecified</pose>
		<truncated>1</truncated>
		<difficult>0</difficult>
		<bndbox>
			<xmin>86</xmin>
			<ymin>1</ymin>
			<xmax>199</xmax>
			<ymax>108</ymax>
		</bndbox>
	</object>
	<object>
		<name>fire</name>
		<pose>Unspecified</pose>
		<truncated>0</truncated>
		<difficult>0</difficult>
		<bndbox>
			<xmin>88</xmin>
			<ymin>117</ymin>
			<xmax>142</xmax>
			<ymax>180</ymax>
		</bndbox>
	</object>
</annotation>
