<annotation>
	<folder>fire</folder>
	<filename>fire_0149.jpg</filename>
	<path>C:\Users\Lenovo\Pictures\forestfire\images\fire\fire_0149.jpg</path>
	<source>
		<database>Unknown</database>
	</source>
	<size>
		<width>224</width>
		<height>224</height>
		<depth>3</depth>
	</size>
	<segmented>0</segmented>
	<object>
		<name>fire</name>
		<pose>Unspecified</pose>
		<truncated>0</truncated>
		<difficult>0</difficult>
		<bndbox>
			<xmin>5</xmin>
			<ymin>91</ymin>
			<xmax>38</xmax>
			<ymax>155</ymax>
		</bndbox>
	</object>
	<object>
		<name>fire</name>
		<pose>Unspecified</pose>
		<truncated>0</truncated>
		<difficult>0</difficult>
		<bndbox>
			<xmin>138</xmin>
			<ymin>135</ymin>
			<xmax>211</xmax>
			<ymax>205</ymax>
		</bndbox>
	</object>
	<object>
		<name>fire</name>
		<pose>Unspecified</pose>
		<truncated>0</truncated>
		<difficult>0</difficult>
		<bndbox>
			<xmin>208</xmin>
			<ymin>108</ymin>
			<xmax>222</xmax>
			<ymax>135</ymax>
		</bndbox>
	</object>
</annotation>
